celery_connectors/__init__.py
celery_connectors/build_ssl_options.py
celery_connectors/kombu_subscriber.py
celery_connectors/message_processor.py
celery_connectors/mixin_send_task_msg.py
celery_connectors/publisher.py
celery_connectors/relay_json_to_celery_worker.py
celery_connectors/relay_worker.py
celery_connectors/run_consumer_relay.py
celery_connectors/run_jtoc_relay.py
celery_connectors/run_publisher.py
celery_connectors/subscriber.py
celery_connectors/utils.py
celery_connectors/log/__init__.py
celery_connectors/log/setup_logging.py
celery_connectors/redis/__init__.py
celery_connectors/redis/base_redis_application.py
celery_connectors/redis/redis-publish-messages.py
celery_connectors/redis/redis-subscribe-and-read-messages.py
celery_connectors/redis/redis_json_application.py
celery_connectors/redis/redis_wrapper.py
celery_connectors-1.0.30.data/scripts/kombu_mixin_subscriber.py
celery_connectors-1.0.30.data/scripts/kombu_rabbitmq_subscriber.py
celery_connectors-1.0.30.data/scripts/kombu_redis_subscriber.py
celery_connectors-1.0.30.data/scripts/kombu_sqs_publisher.py
celery_connectors-1.0.30.data/scripts/kombu_sqs_subscriber.py
celery_connectors-1.0.30.data/scripts/list-bindings.sh
celery_connectors-1.0.30.data/scripts/list-channels.sh
celery_connectors-1.0.30.data/scripts/list-connections.sh
celery_connectors-1.0.30.data/scripts/list-consumers.sh
celery_connectors-1.0.30.data/scripts/list-exchanges.sh
celery_connectors-1.0.30.data/scripts/list-queues.sh
celery_connectors-1.0.30.data/scripts/publish-user-conversion-events-rabbitmq.py
celery_connectors-1.0.30.data/scripts/publish-user-conversion-events-redis.py
celery_connectors-1.0.30.data/scripts/rabbitmqadmin.py
celery_connectors-1.0.30.data/scripts/redis-publish-messages.py
celery_connectors-1.0.30.data/scripts/redis-subscribe-and-read-messages.py
celery_connectors-1.0.30.data/scripts/rmq-close-all-connections.sh
celery_connectors-1.0.30.data/scripts/rmq-status.sh
celery_connectors-1.0.30.dist-info/LICENSE
celery_connectors-1.0.30.dist-info/METADATA
celery_connectors-1.0.30.dist-info/WHEEL
celery_connectors-1.0.30.dist-info/top_level.txt
celery_connectors-1.0.30.dist-info/RECORD
